container_prefab-21.10.172102.data/scripts/prefab
prefab/__init__.py
prefab/cli.py
prefab/color.py
prefab/config.py
prefab/constants.py
prefab/envfile.py
prefab/errors.py
prefab/logger.py
prefab/version.py
prefab/walk.py
prefab/image/__init__.py
prefab/image/docker.py
prefab/image/factory.py
prefab/image/fake.py
prefab/image/graph.py
container_prefab-21.10.172102.dist-info/LICENSE
container_prefab-21.10.172102.dist-info/METADATA
container_prefab-21.10.172102.dist-info/WHEEL
container_prefab-21.10.172102.dist-info/top_level.txt
container_prefab-21.10.172102.dist-info/RECORD
