Metadata-Version: 2.1
Name: container-prefab
Version: 21.10.172102
Summary: Build container images faster ⚡️
Home-page: https://github.com/lexsca/prefab.git
Author: Lex Scarisbrick
Author-email: lex@scarisbrick.org
License: MIT
Platform: UNKNOWN
Classifier: Development Status :: 4 - Beta
Classifier: Intended Audience :: Developers
Classifier: Intended Audience :: Information Technology
Classifier: Intended Audience :: System Administrators
Classifier: License :: OSI Approved :: MIT License
Classifier: Topic :: Software Development :: Build Tools
Classifier: Programming Language :: Python :: 3.7
Classifier: Programming Language :: Python :: 3.8
Classifier: Programming Language :: Python :: 3.9
Classifier: Programming Language :: Python :: 3.10
Requires-Python: >=3.7
License-File: LICENSE
Requires-Dist: docker
Requires-Dist: pyyaml
